spotinstcli/__init__.py
spotinstcli/shim_script.py
spotinstcli/spotfunctions.py
spotinstcli/spotinstcli.py
spotinstcli-0.1.3.dist-info/METADATA
spotinstcli-0.1.3.dist-info/WHEEL
spotinstcli-0.1.3.dist-info/entry_points.txt
spotinstcli-0.1.3.dist-info/top_level.txt
spotinstcli-0.1.3.dist-info/RECORD
