Metadata-Version: 2.1
Name: spotinstcli
Version: 0.1.3
Summary: CLI tool for interacting with Spotinst AWS elasticgroups
Home-page: https://github.com/giladsh1/spotinst-cli
Author: Gilad Sharaby
Author-email: giladsh1@gmail.com
License: UNKNOWN
Keywords: spotinst cli aws spotinst-cli
Platform: UNKNOWN
Classifier: Programming Language :: Python :: 2
Classifier: Programming Language :: Python :: 2.7
Classifier: License :: OSI Approved :: MIT License
Classifier: Operating System :: OS Independent
Requires-Dist: prettytable
Requires-Dist: requests
Requires-Dist: PyInquirer
Requires-Dist: clint
Requires-Dist: wcwidth
